README.md
setup.py
example_app/migrations/0001_initial.py
example_app/migrations/0002_todo_size.py
example_app/migrations/__init__.py
gurutools/__init__.py
gurutools/config.py
gurutools/fields.py
gurutools/filters.py
gurutools/forms.py
gurutools/helpers.py
gurutools/legacymixins.py
gurutools/mixins.py
gurutools/pagination.py
gurutools/s3staticstorage.py
gurutools/spaces.py
gurutools/testutils.py
gurutools.egg-info/PKG-INFO
gurutools.egg-info/SOURCES.txt
gurutools.egg-info/dependency_links.txt
gurutools.egg-info/top_level.txt
gurutools/actions/__init__.py
gurutools/actions/base.py
gurutools/actions/legacy.py
gurutools/actions/mixins.py
gurutools/actions/util.py
gurutools/actions/forms/__init__.py
gurutools/actions/forms/mixins.py
gurutools/actions/tests/__init__.py
gurutools/actions/tests/test_actions.py
gurutools/actions/tests/testutils.py
gurutools/bindings/__init__.py
gurutools/bindings/feed.py
gurutools/bindings/mailer.py
gurutools/bindings/pusher.py
gurutools/bindings/settings.py
gurutools/bindings/testutils.py
gurutools/tests/__init__.py
gurutools/tests/test_dispatcher.py
gurutools/tests/test_forms.py
gurutools/tests/test_helpers.py
gurutools/tests/test_spaces.py