Metadata-Version: 2.1
Name: gurutools
Version: 0.0.27
Summary: A collection of tools we commonly use in Guru services
Home-page: https://gitlab.com/SchoolOrchestration/libs/gurutools
Author: AppointmentGuru
Author-email: tech@appointmentguru.co
License: UNKNOWN
Platform: UNKNOWN
Classifier: Programming Language :: Python :: 3
Classifier: Operating System :: OS Independent
